MofaFangyushu/README.md
MofaFangyushu/__init__.py
MofaFangyushu/__main__.py
MofaFangyushu/file.epub
MofaFangyushu/index.html
MofaFangyushu/css/__init__.py
MofaFangyushu/css/annotations.css
MofaFangyushu/css/main.css
MofaFangyushu/css/normalize.css
MofaFangyushu/css/popup.css
MofaFangyushu/font/__init__.py
MofaFangyushu/font/fontello.eot
MofaFangyushu/font/fontello.svg
MofaFangyushu/font/fontello.ttf
MofaFangyushu/font/fontello.woff
MofaFangyushu/img/__init__.py
MofaFangyushu/img/annotator-glyph-sprite.png
MofaFangyushu/img/annotator-icon-sprite.png
MofaFangyushu/img/apple-touch-icon.png
MofaFangyushu/img/cancelfullscreen.png
MofaFangyushu/img/close.png
MofaFangyushu/img/fullscreen.png
MofaFangyushu/img/loader.gif
MofaFangyushu/img/menu-icon.png
MofaFangyushu/img/save.png
MofaFangyushu/img/saved.png
MofaFangyushu/img/settings-s.png
MofaFangyushu/img/settings.png
MofaFangyushu/img/star.png
MofaFangyushu/js/__init__.py
MofaFangyushu/js/epub.js
MofaFangyushu/js/epub.min.js
MofaFangyushu/js/epub.min.map
MofaFangyushu/js/hooks.min.js
MofaFangyushu/js/hooks.min.map
MofaFangyushu/js/reader.js
MofaFangyushu/js/reader.js.map
MofaFangyushu/js/reader.min.js
MofaFangyushu/js/reader.min.map
MofaFangyushu/js/hooks/__init__.py
MofaFangyushu/js/hooks/extensions/__init__.py
MofaFangyushu/js/hooks/extensions/highlight.js
MofaFangyushu/js/libs/__init__.py
MofaFangyushu/js/libs/jquery.min.js
MofaFangyushu/js/libs/localforage.min.js
MofaFangyushu/js/libs/screenfull.js
MofaFangyushu/js/libs/screenfull.min.js
MofaFangyushu/js/libs/zip.min.js
MofaFangyushu/js/plugins/__init__.py
MofaFangyushu/js/plugins/hypothesis.js
MofaFangyushu/js/plugins/search.js
mofa_fangyushu-2022.9.29.0.dist-info/METADATA
mofa_fangyushu-2022.9.29.0.dist-info/WHEEL
mofa_fangyushu-2022.9.29.0.dist-info/entry_points.txt
mofa_fangyushu-2022.9.29.0.dist-info/top_level.txt
mofa_fangyushu-2022.9.29.0.dist-info/RECORD
